{
  "legislative_session": "2025-2026",
  "identifier": "HR 71",
  "title": "A Concurrent Resolution establishing the Pennsylvania State Flag Commission to study the history of the State flag of the Commonwealth, solicit design submissions for a new State flag and recommend changes to the State flag.",
  "from_organization": "~{\"classification\": \"lower\"}",
  "classification": [
    "resolution"
  ],
  "subject": [],
  "abstracts": [],
  "other_titles": [],
  "other_identifiers": [],
  "actions": [
    {
      "description": "Referred to State Government",
      "date": "2025-02-12T05:00:00+00:00",
      "organization_id": "~{\"classification\": \"lower\"}",
      "classification": [
        "referral-committee"
      ],
      "related_entities": [],
      "_processing": {
        "log_file_created": "2025-10-25T03:31:42Z"
      }
    }
  ],
  "sponsorships": [
    {
      "name": "Joe Webster",
      "classification": "primary",
      "entity_type": "person",
      "primary": true,
      "person_id": "~{\"chamber\": \"lower\", \"name\": \"Joe Webster\"}",
      "organization_id": null
    },
    {
      "name": "Arvind Venkat",
      "classification": "cosponsor",
      "entity_type": "person",
      "primary": false,
      "person_id": "~{\"chamber\": \"lower\", \"name\": \"Arvind Venkat\"}",
      "organization_id": null
    },
    {
      "name": "Tarik Khan",
      "classification": "cosponsor",
      "entity_type": "person",
      "primary": false,
      "person_id": "~{\"chamber\": \"lower\", \"name\": \"Tarik Khan\"}",
      "organization_id": null
    },
    {
      "name": "Benjamin Sanchez",
      "classification": "cosponsor",
      "entity_type": "person",
      "primary": false,
      "person_id": "~{\"chamber\": \"lower\", \"name\": \"Benjamin Sanchez\"}",
      "organization_id": null
    },
    {
      "name": "Ben Waxman",
      "classification": "cosponsor",
      "entity_type": "person",
      "primary": false,
      "person_id": "~{\"chamber\": \"lower\", \"name\": \"Ben Waxman\"}",
      "organization_id": null
    },
    {
      "name": "Jim Haddock",
      "classification": "cosponsor",
      "entity_type": "person",
      "primary": false,
      "person_id": "~{\"chamber\": \"lower\", \"name\": \"Jim Haddock\"}",
      "organization_id": null
    },
    {
      "name": "Keith Harris",
      "classification": "cosponsor",
      "entity_type": "person",
      "primary": false,
      "person_id": "~{\"chamber\": \"lower\", \"name\": \"Keith Harris\"}",
      "organization_id": null
    }
  ],
  "related_bills": [],
  "versions": [
    {
      "note": "Printer's No. PN0583",
      "links": [
        {
          "url": "https://www.palegis.us/legislation/bills/text/PDF/2025/0/HR0071/PN0583",
          "media_type": "application/pdf"
        },
        {
          "url": "https://www.palegis.us/legislation/bills/text/HTM/2025/0/HR0071/PN0583",
          "media_type": "text/html"
        },
        {
          "url": "https://www.palegis.us/legislation/bills/text/DOC/2025/0/HR0071/PN0583",
          "media_type": "application/msword"
        }
      ],
      "date": "",
      "classification": ""
    }
  ],
  "documents": [],
  "citations": [],
  "sources": [
    {
      "url": "https://www.palegis.us/legislation/bills/2025/hr71",
      "note": ""
    }
  ],
  "extras": {},
  "jurisdiction": {
    "id": "ocd-jurisdiction/country:us/state:pa/government",
    "name": "Pennsylvania",
    "classification": "state",
    "division_id": "ocd-division/country:us/state:pa"
  },
  "_processing": {
    "logs_latest_update": "2025-10-25T03:31:42Z",
    "text_extraction_latest_update": "2025-10-25T08:31:44.338715Z"
  }
}