{
  "legislative_session": "2025-2026",
  "identifier": "HR 302",
  "title": "A Resolution ensuring greater access to sickle cell disease treatments and designating the Department of Health to conduct a comprehensive and coordinated data collection effort to better understand and quantify the scope and impact of sickle cell disease on patients, communities and states throughout the United States.",
  "from_organization": "~{\"classification\": \"lower\"}",
  "classification": [
    "resolution"
  ],
  "subject": [],
  "abstracts": [],
  "other_titles": [],
  "other_identifiers": [],
  "actions": [
    {
      "description": "Referred to Health",
      "date": "2025-09-04T04:00:00+00:00",
      "organization_id": "~{\"classification\": \"lower\"}",
      "classification": [
        "referral-committee"
      ],
      "related_entities": [],
      "_processing": {
        "log_file_created": "2025-10-25T03:31:45Z"
      }
    }
  ],
  "sponsorships": [
    {
      "name": "Greg Scott",
      "classification": "primary",
      "entity_type": "person",
      "primary": true,
      "person_id": "~{\"chamber\": \"lower\", \"name\": \"Greg Scott\"}",
      "organization_id": null
    },
    {
      "name": "Jose Giral",
      "classification": "cosponsor",
      "entity_type": "person",
      "primary": false,
      "person_id": "~{\"chamber\": \"lower\", \"name\": \"Jose Giral\"}",
      "organization_id": null
    },
    {
      "name": "Patrick Harkins",
      "classification": "cosponsor",
      "entity_type": "person",
      "primary": false,
      "person_id": "~{\"chamber\": \"lower\", \"name\": \"Patrick Harkins\"}",
      "organization_id": null
    },
    {
      "name": "Jeanne Mcneill",
      "classification": "cosponsor",
      "entity_type": "person",
      "primary": false,
      "person_id": "~{\"chamber\": \"lower\", \"name\": \"Jeanne Mcneill\"}",
      "organization_id": null
    },
    {
      "name": "Ben Waxman",
      "classification": "cosponsor",
      "entity_type": "person",
      "primary": false,
      "person_id": "~{\"chamber\": \"lower\", \"name\": \"Ben Waxman\"}",
      "organization_id": null
    },
    {
      "name": "Carol Hill-Evans",
      "classification": "cosponsor",
      "entity_type": "person",
      "primary": false,
      "person_id": "~{\"chamber\": \"lower\", \"name\": \"Carol Hill-Evans\"}",
      "organization_id": null
    },
    {
      "name": "Benjamin Sanchez",
      "classification": "cosponsor",
      "entity_type": "person",
      "primary": false,
      "person_id": "~{\"chamber\": \"lower\", \"name\": \"Benjamin Sanchez\"}",
      "organization_id": null
    },
    {
      "name": "Johanny Cepeda-Freytiz",
      "classification": "cosponsor",
      "entity_type": "person",
      "primary": false,
      "person_id": "~{\"chamber\": \"lower\", \"name\": \"Johanny Cepeda-Freytiz\"}",
      "organization_id": null
    },
    {
      "name": "La'Tasha Mayes",
      "classification": "cosponsor",
      "entity_type": "person",
      "primary": false,
      "person_id": "~{\"chamber\": \"lower\", \"name\": \"La'Tasha Mayes\"}",
      "organization_id": null
    },
    {
      "name": "Joseph Hohenstein",
      "classification": "cosponsor",
      "entity_type": "person",
      "primary": false,
      "person_id": "~{\"chamber\": \"lower\", \"name\": \"Joseph Hohenstein\"}",
      "organization_id": null
    },
    {
      "name": "Jill Cooper",
      "classification": "cosponsor",
      "entity_type": "person",
      "primary": false,
      "person_id": "~{\"chamber\": \"lower\", \"name\": \"Jill Cooper\"}",
      "organization_id": null
    },
    {
      "name": "Dan Williams",
      "classification": "cosponsor",
      "entity_type": "person",
      "primary": false,
      "person_id": "~{\"chamber\": \"lower\", \"name\": \"Dan Williams\"}",
      "organization_id": null
    }
  ],
  "related_bills": [],
  "versions": [
    {
      "note": "Printer's No. PN2261",
      "links": [
        {
          "url": "https://www.palegis.us/legislation/bills/text/PDF/2025/0/HR0302/PN2261",
          "media_type": "application/pdf"
        },
        {
          "url": "https://www.palegis.us/legislation/bills/text/HTM/2025/0/HR0302/PN2261",
          "media_type": "text/html"
        },
        {
          "url": "https://www.palegis.us/legislation/bills/text/DOC/2025/0/HR0302/PN2261",
          "media_type": "application/msword"
        }
      ],
      "date": "",
      "classification": ""
    }
  ],
  "documents": [],
  "citations": [],
  "sources": [
    {
      "url": "https://www.palegis.us/legislation/bills/2025/hr302",
      "note": ""
    }
  ],
  "extras": {},
  "jurisdiction": {
    "id": "ocd-jurisdiction/country:us/state:pa/government",
    "name": "Pennsylvania",
    "classification": "state",
    "division_id": "ocd-division/country:us/state:pa"
  },
  "_processing": {
    "logs_latest_update": "2025-10-25T03:31:45Z",
    "text_extraction_latest_update": "2025-10-25T09:31:20.482698Z"
  }
}