{
  "legislative_session": "2025-2026",
  "identifier": "SB 862",
  "title": "An Act amending Title 8 (Boroughs and Incorporated Towns) of the Pennsylvania Consolidated Statutes, in vacancies in office, further providing for filling vacancies in elective borough offices.",
  "from_organization": "~{\"classification\": \"upper\"}",
  "classification": [
    "bill"
  ],
  "subject": [],
  "abstracts": [],
  "other_titles": [],
  "other_identifiers": [],
  "actions": [
    {
      "description": "Referred to Local Government",
      "date": "2025-06-19T04:00:00+00:00",
      "organization_id": "~{\"classification\": \"upper\"}",
      "classification": [
        "referral-committee"
      ],
      "related_entities": [],
      "_processing": {
        "log_file_created": "2025-10-25T03:31:44Z"
      }
    },
    {
      "description": "Reported as committed",
      "date": "2025-10-07T04:00:00+00:00",
      "organization_id": "~{\"classification\": \"upper\"}",
      "classification": [
        "committee-passage"
      ],
      "related_entities": [],
      "_processing": {
        "log_file_created": "2025-10-25T03:31:44Z"
      }
    },
    {
      "description": "First consideration",
      "date": "2025-10-07T04:00:00+00:00",
      "organization_id": "~{\"classification\": \"upper\"}",
      "classification": [
        "reading-1"
      ],
      "related_entities": [],
      "_processing": {
        "log_file_created": "2025-10-25T03:31:44Z"
      }
    },
    {
      "description": "Second consideration",
      "date": "2025-10-08T04:00:00+00:00",
      "organization_id": "~{\"classification\": \"upper\"}",
      "classification": [
        "reading-2"
      ],
      "related_entities": [],
      "_processing": {
        "log_file_created": "2025-10-25T03:31:44Z"
      }
    },
    {
      "description": "Re-referred to Appropriations",
      "date": "2025-10-08T04:00:00+00:00",
      "organization_id": "~{\"classification\": \"upper\"}",
      "classification": [
        "referral-committee"
      ],
      "related_entities": [],
      "_processing": {
        "log_file_created": "2025-10-25T03:31:44Z"
      }
    }
  ],
  "sponsorships": [
    {
      "name": "Patty Kim",
      "classification": "primary",
      "entity_type": "person",
      "primary": true,
      "person_id": "~{\"chamber\": \"upper\", \"name\": \"Patty Kim\"}",
      "organization_id": null
    },
    {
      "name": "Scott Hutchinson",
      "classification": "cosponsor",
      "entity_type": "person",
      "primary": false,
      "person_id": "~{\"chamber\": \"upper\", \"name\": \"Scott Hutchinson\"}",
      "organization_id": null
    },
    {
      "name": "Cris Dush",
      "classification": "cosponsor",
      "entity_type": "person",
      "primary": false,
      "person_id": "~{\"chamber\": \"upper\", \"name\": \"Cris Dush\"}",
      "organization_id": null
    },
    {
      "name": "Dawn Keefer",
      "classification": "cosponsor",
      "entity_type": "person",
      "primary": false,
      "person_id": "~{\"chamber\": \"upper\", \"name\": \"Dawn Keefer\"}",
      "organization_id": null
    },
    {
      "name": "Timothy Kearney",
      "classification": "cosponsor",
      "entity_type": "person",
      "primary": false,
      "person_id": "~{\"chamber\": \"upper\", \"name\": \"Timothy Kearney\"}",
      "organization_id": null
    },
    {
      "name": "Tracy Pennycuick",
      "classification": "cosponsor",
      "entity_type": "person",
      "primary": false,
      "person_id": "~{\"chamber\": \"upper\", \"name\": \"Tracy Pennycuick\"}",
      "organization_id": null
    },
    {
      "name": "Wayne Fontana",
      "classification": "cosponsor",
      "entity_type": "person",
      "primary": false,
      "person_id": "~{\"chamber\": \"upper\", \"name\": \"Wayne Fontana\"}",
      "organization_id": null
    },
    {
      "name": "Rosemary Brown",
      "classification": "cosponsor",
      "entity_type": "person",
      "primary": false,
      "person_id": "~{\"chamber\": \"upper\", \"name\": \"Rosemary Brown\"}",
      "organization_id": null
    },
    {
      "name": "Jay Costa",
      "classification": "cosponsor",
      "entity_type": "person",
      "primary": false,
      "person_id": "~{\"chamber\": \"upper\", \"name\": \"Jay Costa\"}",
      "organization_id": null
    },
    {
      "name": "Elder Vogel",
      "classification": "cosponsor",
      "entity_type": "person",
      "primary": false,
      "person_id": "~{\"chamber\": \"upper\", \"name\": \"Elder Vogel\"}",
      "organization_id": null
    },
    {
      "name": "Judy Ward",
      "classification": "cosponsor",
      "entity_type": "person",
      "primary": false,
      "person_id": "~{\"chamber\": \"upper\", \"name\": \"Judy Ward\"}",
      "organization_id": null
    }
  ],
  "related_bills": [],
  "versions": [
    {
      "note": "Printer's No. PN0973",
      "links": [
        {
          "url": "https://www.palegis.us/legislation/bills/text/PDF/2025/0/SB0862/PN0973",
          "media_type": "application/pdf"
        },
        {
          "url": "https://www.palegis.us/legislation/bills/text/HTM/2025/0/SB0862/PN0973",
          "media_type": "text/html"
        },
        {
          "url": "https://www.palegis.us/legislation/bills/text/DOC/2025/0/SB0862/PN0973",
          "media_type": "application/msword"
        }
      ],
      "date": "",
      "classification": ""
    }
  ],
  "documents": [],
  "citations": [],
  "sources": [
    {
      "url": "https://www.palegis.us/legislation/bills/2025/sb862",
      "note": ""
    },
    {
      "url": "https://www.palegis.us/senate/committees/roll-call-votes/vote-list/vote-summary?committeecode=15&rollcallid=462&sessYr=2025&sessInd=0",
      "note": ""
    }
  ],
  "extras": {},
  "jurisdiction": {
    "id": "ocd-jurisdiction/country:us/state:pa/government",
    "name": "Pennsylvania",
    "classification": "state",
    "division_id": "ocd-division/country:us/state:pa"
  },
  "_processing": {
    "logs_latest_update": "2025-10-25T03:31:44Z"
  }
}