{
  "legislative_session": "2025-2026",
  "identifier": "HB 627",
  "title": "An Act amending the act of November 22, 1978 (P.L.1166, No.274), referred to as the Pennsylvania Commission on Crime and Delinquency Law, providing for Public Safety Resident Communications Pilot Program.",
  "from_organization": "~{\"classification\": \"lower\"}",
  "classification": [
    "bill"
  ],
  "subject": [],
  "abstracts": [],
  "other_titles": [],
  "other_identifiers": [],
  "actions": [
    {
      "description": "Referred to Communications & Technology",
      "date": "2025-02-20T05:00:00+00:00",
      "organization_id": "~{\"classification\": \"lower\"}",
      "classification": [
        "referral-committee"
      ],
      "related_entities": [],
      "_processing": {
        "log_file_created": "2025-10-25T03:31:43Z"
      }
    },
    {
      "description": "Reported as committed",
      "date": "2025-06-03T04:00:00+00:00",
      "organization_id": "~{\"classification\": \"lower\"}",
      "classification": [
        "committee-passage"
      ],
      "related_entities": [],
      "_processing": {
        "log_file_created": "2025-10-25T03:31:43Z"
      }
    },
    {
      "description": "First consideration",
      "date": "2025-06-03T04:00:00+00:00",
      "organization_id": "~{\"classification\": \"lower\"}",
      "classification": [
        "reading-1"
      ],
      "related_entities": [],
      "_processing": {
        "log_file_created": "2025-10-25T03:31:43Z"
      }
    },
    {
      "description": "Re-committed to Rules",
      "date": "2025-06-03T04:00:00+00:00",
      "organization_id": "~{\"classification\": \"lower\"}",
      "classification": [
        "referral-committee"
      ],
      "related_entities": [],
      "_processing": {
        "log_file_created": "2025-10-25T03:31:43Z"
      }
    },
    {
      "description": "Re-reported as committed",
      "date": "2025-06-17T04:00:00+00:00",
      "organization_id": "~{\"classification\": \"lower\"}",
      "classification": [
        "committee-passage"
      ],
      "related_entities": [],
      "_processing": {
        "log_file_created": "2025-10-25T03:31:43Z"
      }
    },
    {
      "description": "Second consideration, with amendments",
      "date": "2025-06-17T04:00:00+00:00",
      "organization_id": "~{\"classification\": \"lower\"}",
      "classification": [
        "reading-2"
      ],
      "related_entities": [],
      "_processing": {
        "log_file_created": "2025-10-25T03:31:43Z"
      }
    },
    {
      "description": "Re-committed to Appropriations",
      "date": "2025-06-17T04:00:00+00:00",
      "organization_id": "~{\"classification\": \"lower\"}",
      "classification": [
        "referral-committee"
      ],
      "related_entities": [],
      "_processing": {
        "log_file_created": "2025-10-25T03:31:43Z"
      }
    },
    {
      "description": "Re-reported as committed",
      "date": "2025-06-23T04:00:00+00:00",
      "organization_id": "~{\"classification\": \"lower\"}",
      "classification": [
        "committee-passage"
      ],
      "related_entities": [],
      "_processing": {
        "log_file_created": "2025-10-25T03:31:43Z"
      }
    },
    {
      "description": "Third consideration and final passage",
      "date": "2025-06-23T04:00:00+00:00",
      "organization_id": "~{\"classification\": \"lower\"}",
      "classification": [
        "passage",
        "reading-3"
      ],
      "related_entities": [],
      "_processing": {
        "log_file_created": "2025-10-25T03:31:43Z"
      }
    },
    {
      "description": "Referred to Law & Justice",
      "date": "2025-06-24T04:00:00+00:00",
      "organization_id": "~{\"classification\": \"upper\"}",
      "classification": [
        "referral-committee"
      ],
      "related_entities": [],
      "_processing": {
        "log_file_created": "2025-10-25T03:31:43Z"
      }
    }
  ],
  "sponsorships": [
    {
      "name": "Jared Solomon",
      "classification": "primary",
      "entity_type": "person",
      "primary": true,
      "person_id": "~{\"chamber\": \"lower\", \"name\": \"Jared Solomon\"}",
      "organization_id": null
    },
    {
      "name": "Carol Hill-Evans",
      "classification": "cosponsor",
      "entity_type": "person",
      "primary": false,
      "person_id": "~{\"chamber\": \"lower\", \"name\": \"Carol Hill-Evans\"}",
      "organization_id": null
    },
    {
      "name": "Johanny Cepeda-Freytiz",
      "classification": "cosponsor",
      "entity_type": "person",
      "primary": false,
      "person_id": "~{\"chamber\": \"lower\", \"name\": \"Johanny Cepeda-Freytiz\"}",
      "organization_id": null
    },
    {
      "name": "Melissa Cerrato",
      "classification": "cosponsor",
      "entity_type": "person",
      "primary": false,
      "person_id": "~{\"chamber\": \"lower\", \"name\": \"Melissa Cerrato\"}",
      "organization_id": null
    },
    {
      "name": "Benjamin Sanchez",
      "classification": "cosponsor",
      "entity_type": "person",
      "primary": false,
      "person_id": "~{\"chamber\": \"lower\", \"name\": \"Benjamin Sanchez\"}",
      "organization_id": null
    },
    {
      "name": "G. Roni Green",
      "classification": "cosponsor",
      "entity_type": "person",
      "primary": false,
      "person_id": "~{\"chamber\": \"lower\", \"name\": \"G. Roni Green\"}",
      "organization_id": null
    },
    {
      "name": "Sean Dougherty",
      "classification": "cosponsor",
      "entity_type": "person",
      "primary": false,
      "person_id": "~{\"chamber\": \"lower\", \"name\": \"Sean Dougherty\"}",
      "organization_id": null
    },
    {
      "name": "Joe Webster",
      "classification": "cosponsor",
      "entity_type": "person",
      "primary": false,
      "person_id": "~{\"chamber\": \"lower\", \"name\": \"Joe Webster\"}",
      "organization_id": null
    }
  ],
  "related_bills": [],
  "versions": [
    {
      "note": "Printer's No. PN1947",
      "links": [
        {
          "url": "https://www.palegis.us/legislation/bills/text/PDF/2025/0/HB0627/PN1947",
          "media_type": "application/pdf"
        },
        {
          "url": "https://www.palegis.us/legislation/bills/text/HTM/2025/0/HB0627/PN1947",
          "media_type": "text/html"
        },
        {
          "url": "https://www.palegis.us/legislation/bills/text/DOC/2025/0/HB0627/PN1947",
          "media_type": "application/msword"
        }
      ],
      "date": "",
      "classification": ""
    },
    {
      "note": "Printer's No. PN0638",
      "links": [
        {
          "url": "https://www.palegis.us/legislation/bills/text/PDF/2025/0/HB0627/PN0638",
          "media_type": "application/pdf"
        },
        {
          "url": "https://www.palegis.us/legislation/bills/text/HTM/2025/0/HB0627/PN0638",
          "media_type": "text/html"
        },
        {
          "url": "https://www.palegis.us/legislation/bills/text/DOC/2025/0/HB0627/PN0638",
          "media_type": "application/msword"
        }
      ],
      "date": "",
      "classification": ""
    }
  ],
  "documents": [
    {
      "note": "House Fiscal Note",
      "links": [
        {
          "url": "https://www.legis.state.pa.us/WU01/LI/BI/FN/2025/0/HB0627P1947.pdf",
          "media_type": "application/pdf"
        }
      ],
      "date": "",
      "classification": ""
    }
  ],
  "citations": [],
  "sources": [
    {
      "url": "https://www.palegis.us/legislation/bills/2025/hb627",
      "note": ""
    },
    {
      "url": "https://www.palegis.us/house/roll-calls/summary?sessYr=2025&sessInd=0&rcNum=431",
      "note": ""
    },
    {
      "url": "https://www.palegis.us/house/committees/roll-call-votes/vote-list/vote-summary?committeecode=62&rollcallid=849&sessYr=2025&sessInd=0",
      "note": ""
    },
    {
      "url": "https://www.palegis.us/house/roll-calls/summary?sessYr=2025&sessInd=0&rcNum=408",
      "note": ""
    },
    {
      "url": "https://www.palegis.us/house/committees/roll-call-votes/vote-list/vote-summary?committeecode=67&rollcallid=801&sessYr=2025&sessInd=0",
      "note": ""
    },
    {
      "url": "https://www.palegis.us/house/committees/roll-call-votes/vote-list/vote-summary?committeecode=68&rollcallid=611&sessYr=2025&sessInd=0",
      "note": ""
    }
  ],
  "extras": {},
  "jurisdiction": {
    "id": "ocd-jurisdiction/country:us/state:pa/government",
    "name": "Pennsylvania",
    "classification": "state",
    "division_id": "ocd-division/country:us/state:pa"
  },
  "_processing": {
    "logs_latest_update": "2025-10-25T03:31:43Z"
  }
}