{
  "legislative_session": "2025-2026",
  "identifier": "HB 339",
  "title": "An Act amending the act of March 10, 1949 (P.L.30, No.14), known as the Public School Code of 1949, in terms and courses of study, providing for mental health check-ins.",
  "from_organization": "~{\"classification\": \"lower\"}",
  "classification": [
    "bill"
  ],
  "subject": [],
  "abstracts": [],
  "other_titles": [],
  "other_identifiers": [],
  "actions": [
    {
      "description": "Referred to Education",
      "date": "2025-01-27T05:00:00+00:00",
      "organization_id": "~{\"classification\": \"lower\"}",
      "classification": [
        "referral-committee"
      ],
      "related_entities": [],
      "_processing": {
        "log_file_created": "2025-10-25T03:31:45Z"
      }
    }
  ],
  "sponsorships": [
    {
      "name": "G. Roni Green",
      "classification": "primary",
      "entity_type": "person",
      "primary": true,
      "person_id": "~{\"chamber\": \"lower\", \"name\": \"G. Roni Green\"}",
      "organization_id": null
    },
    {
      "name": "Jose Giral",
      "classification": "cosponsor",
      "entity_type": "person",
      "primary": false,
      "person_id": "~{\"chamber\": \"lower\", \"name\": \"Jose Giral\"}",
      "organization_id": null
    },
    {
      "name": "Kristine Howard",
      "classification": "cosponsor",
      "entity_type": "person",
      "primary": false,
      "person_id": "~{\"chamber\": \"lower\", \"name\": \"Kristine Howard\"}",
      "organization_id": null
    },
    {
      "name": "Benjamin Sanchez",
      "classification": "cosponsor",
      "entity_type": "person",
      "primary": false,
      "person_id": "~{\"chamber\": \"lower\", \"name\": \"Benjamin Sanchez\"}",
      "organization_id": null
    },
    {
      "name": "Joseph Hohenstein",
      "classification": "cosponsor",
      "entity_type": "person",
      "primary": false,
      "person_id": "~{\"chamber\": \"lower\", \"name\": \"Joseph Hohenstein\"}",
      "organization_id": null
    },
    {
      "name": "Darisha K. Parker",
      "classification": "cosponsor",
      "entity_type": "person",
      "primary": false,
      "person_id": "~{\"chamber\": \"lower\", \"name\": \"Darisha K. Parker\"}",
      "organization_id": null
    },
    {
      "name": "Anthony Bellmon",
      "classification": "cosponsor",
      "entity_type": "person",
      "primary": false,
      "person_id": "~{\"chamber\": \"lower\", \"name\": \"Anthony Bellmon\"}",
      "organization_id": null
    },
    {
      "name": "Justin Fleming",
      "classification": "cosponsor",
      "entity_type": "person",
      "primary": false,
      "person_id": "~{\"chamber\": \"lower\", \"name\": \"Justin Fleming\"}",
      "organization_id": null
    }
  ],
  "related_bills": [],
  "versions": [
    {
      "note": "Printer's No. PN0294",
      "links": [
        {
          "url": "https://www.palegis.us/legislation/bills/text/PDF/2025/0/HB0339/PN0294",
          "media_type": "application/pdf"
        },
        {
          "url": "https://www.palegis.us/legislation/bills/text/HTM/2025/0/HB0339/PN0294",
          "media_type": "text/html"
        },
        {
          "url": "https://www.palegis.us/legislation/bills/text/DOC/2025/0/HB0339/PN0294",
          "media_type": "application/msword"
        }
      ],
      "date": "",
      "classification": ""
    }
  ],
  "documents": [],
  "citations": [],
  "sources": [
    {
      "url": "https://www.palegis.us/legislation/bills/2025/hb339",
      "note": ""
    }
  ],
  "extras": {},
  "jurisdiction": {
    "id": "ocd-jurisdiction/country:us/state:pa/government",
    "name": "Pennsylvania",
    "classification": "state",
    "division_id": "ocd-division/country:us/state:pa"
  },
  "_processing": {
    "logs_latest_update": "2025-10-25T03:31:45Z",
    "text_extraction_latest_update": "2025-10-25T09:13:27.577388Z"
  }
}