{
  "legislative_session": "2025-2026",
  "identifier": "SB 157",
  "title": "An Act amending the act of June 13, 1967 (P.L.31, No.21), known as the Human Services Code, in public assistance, further providing for reports to General Assembly.",
  "from_organization": "~{\"classification\": \"upper\"}",
  "classification": [
    "bill"
  ],
  "subject": [],
  "abstracts": [],
  "other_titles": [],
  "other_identifiers": [],
  "actions": [
    {
      "description": "Referred to Health & Human Services",
      "date": "2025-01-23T05:00:00+00:00",
      "organization_id": "~{\"classification\": \"upper\"}",
      "classification": [
        "referral-committee"
      ],
      "related_entities": [],
      "_processing": {
        "log_file_created": "2025-10-25T03:31:41Z"
      }
    },
    {
      "description": "Reported as committed",
      "date": "2025-01-27T05:00:00+00:00",
      "organization_id": "~{\"classification\": \"upper\"}",
      "classification": [
        "committee-passage"
      ],
      "related_entities": [],
      "_processing": {
        "log_file_created": "2025-10-25T03:31:41Z"
      }
    },
    {
      "description": "First consideration",
      "date": "2025-01-27T05:00:00+00:00",
      "organization_id": "~{\"classification\": \"upper\"}",
      "classification": [
        "reading-1"
      ],
      "related_entities": [],
      "_processing": {
        "log_file_created": "2025-10-25T03:31:41Z"
      }
    },
    {
      "description": "Second consideration",
      "date": "2025-01-28T05:00:00+00:00",
      "organization_id": "~{\"classification\": \"upper\"}",
      "classification": [
        "reading-2"
      ],
      "related_entities": [],
      "_processing": {
        "log_file_created": "2025-10-25T03:31:41Z"
      }
    },
    {
      "description": "Re-referred to Appropriations",
      "date": "2025-01-28T05:00:00+00:00",
      "organization_id": "~{\"classification\": \"upper\"}",
      "classification": [
        "referral-committee"
      ],
      "related_entities": [],
      "_processing": {
        "log_file_created": "2025-10-25T03:31:41Z"
      }
    },
    {
      "description": "Re-reported as committed",
      "date": "2025-01-29T05:00:00+00:00",
      "organization_id": "~{\"classification\": \"upper\"}",
      "classification": [
        "committee-passage"
      ],
      "related_entities": [],
      "_processing": {
        "log_file_created": "2025-10-25T03:31:41Z"
      }
    },
    {
      "description": "Third consideration and final passage",
      "date": "2025-01-29T05:00:00+00:00",
      "organization_id": "~{\"classification\": \"upper\"}",
      "classification": [
        "passage",
        "reading-3"
      ],
      "related_entities": [],
      "_processing": {
        "log_file_created": "2025-10-25T03:31:41Z"
      }
    },
    {
      "description": "Referred to Human Services",
      "date": "2025-01-29T05:00:00+00:00",
      "organization_id": "~{\"classification\": \"lower\"}",
      "classification": [
        "referral-committee"
      ],
      "related_entities": [],
      "_processing": {
        "log_file_created": "2025-10-25T03:31:41Z"
      }
    }
  ],
  "sponsorships": [
    {
      "name": "David Argall",
      "classification": "primary",
      "entity_type": "person",
      "primary": true,
      "person_id": "~{\"chamber\": \"upper\", \"name\": \"David Argall\"}",
      "organization_id": null
    },
    {
      "name": "Scott Martin",
      "classification": "cosponsor",
      "entity_type": "person",
      "primary": false,
      "person_id": "~{\"chamber\": \"upper\", \"name\": \"Scott Martin\"}",
      "organization_id": null
    },
    {
      "name": "Greg Rothman",
      "classification": "cosponsor",
      "entity_type": "person",
      "primary": false,
      "person_id": "~{\"chamber\": \"upper\", \"name\": \"Greg Rothman\"}",
      "organization_id": null
    },
    {
      "name": "Jarrett Coleman",
      "classification": "cosponsor",
      "entity_type": "person",
      "primary": false,
      "person_id": "~{\"chamber\": \"upper\", \"name\": \"Jarrett Coleman\"}",
      "organization_id": null
    },
    {
      "name": "Judy Ward",
      "classification": "cosponsor",
      "entity_type": "person",
      "primary": false,
      "person_id": "~{\"chamber\": \"upper\", \"name\": \"Judy Ward\"}",
      "organization_id": null
    },
    {
      "name": "Scott Hutchinson",
      "classification": "cosponsor",
      "entity_type": "person",
      "primary": false,
      "person_id": "~{\"chamber\": \"upper\", \"name\": \"Scott Hutchinson\"}",
      "organization_id": null
    },
    {
      "name": "Lisa Baker",
      "classification": "cosponsor",
      "entity_type": "person",
      "primary": false,
      "person_id": "~{\"chamber\": \"upper\", \"name\": \"Lisa Baker\"}",
      "organization_id": null
    },
    {
      "name": "Elder Vogel",
      "classification": "cosponsor",
      "entity_type": "person",
      "primary": false,
      "person_id": "~{\"chamber\": \"upper\", \"name\": \"Elder Vogel\"}",
      "organization_id": null
    },
    {
      "name": "Kristin Phillips-Hill",
      "classification": "cosponsor",
      "entity_type": "person",
      "primary": false,
      "person_id": "~{\"chamber\": \"upper\", \"name\": \"Kristin Phillips-Hill\"}",
      "organization_id": null
    },
    {
      "name": "Lynda Schlegel Culver",
      "classification": "cosponsor",
      "entity_type": "person",
      "primary": false,
      "person_id": "~{\"chamber\": \"upper\", \"name\": \"Lynda Schlegel Culver\"}",
      "organization_id": null
    },
    {
      "name": "Patrick Stefano",
      "classification": "cosponsor",
      "entity_type": "person",
      "primary": false,
      "person_id": "~{\"chamber\": \"upper\", \"name\": \"Patrick Stefano\"}",
      "organization_id": null
    }
  ],
  "related_bills": [],
  "versions": [
    {
      "note": "Printer's No. PN0107",
      "links": [
        {
          "url": "https://www.palegis.us/legislation/bills/text/PDF/2025/0/SB0157/PN0107",
          "media_type": "application/pdf"
        },
        {
          "url": "https://www.palegis.us/legislation/bills/text/HTM/2025/0/SB0157/PN0107",
          "media_type": "text/html"
        },
        {
          "url": "https://www.palegis.us/legislation/bills/text/DOC/2025/0/SB0157/PN0107",
          "media_type": "application/msword"
        }
      ],
      "date": "",
      "classification": ""
    }
  ],
  "documents": [
    {
      "note": "Senate Fiscal Note",
      "links": [
        {
          "url": "https://www.legis.state.pa.us/WU01/LI/BI/SFN/2025/0/SB0157P0107.pdf",
          "media_type": "application/pdf"
        }
      ],
      "date": "",
      "classification": ""
    }
  ],
  "citations": [],
  "sources": [
    {
      "url": "https://www.palegis.us/legislation/bills/2025/sb157",
      "note": ""
    },
    {
      "url": "https://www.palegis.us/senate/roll-calls/summary?sessYr=2025&sessInd=0&rcNum=15",
      "note": ""
    },
    {
      "url": "https://www.palegis.us/senate/committees/roll-call-votes/vote-list/vote-summary?committeecode=3&rollcallid=28&sessYr=2025&sessInd=0",
      "note": ""
    },
    {
      "url": "https://www.palegis.us/senate/committees/roll-call-votes/vote-list/vote-summary?committeecode=33&rollcallid=4&sessYr=2025&sessInd=0",
      "note": ""
    }
  ],
  "extras": {},
  "jurisdiction": {
    "id": "ocd-jurisdiction/country:us/state:pa/government",
    "name": "Pennsylvania",
    "classification": "state",
    "division_id": "ocd-division/country:us/state:pa"
  },
  "_processing": {
    "logs_latest_update": "2025-10-25T03:31:41Z"
  }
}