{
  "legislative_session": "2025-2026",
  "identifier": "HB 610",
  "title": "An Act amending the act of April 9, 1929 (P.L.177, No.175), known as The Administrative Code of 1929, in public works employment verification, further providing for definitions, for duty of public works contractors and subcontractors, for verification form, for violations, for enforcement and sanctions, for Public Works Employment Verification Account, for protection from retaliation, for good faith immunity and for public works contractor and subcontractor liability; and making an editorial change.",
  "from_organization": "~{\"classification\": \"lower\"}",
  "classification": [
    "bill"
  ],
  "subject": [],
  "abstracts": [],
  "other_titles": [],
  "other_identifiers": [],
  "actions": [
    {
      "description": "Referred to Labor & Industry",
      "date": "2025-02-20T05:00:00+00:00",
      "organization_id": "~{\"classification\": \"lower\"}",
      "classification": [
        "referral-committee"
      ],
      "related_entities": [],
      "_processing": {
        "log_file_created": "2025-10-25T03:31:41Z"
      }
    }
  ],
  "sponsorships": [
    {
      "name": "Milou Mackenzie",
      "classification": "primary",
      "entity_type": "person",
      "primary": true,
      "person_id": "~{\"chamber\": \"lower\", \"name\": \"Milou Mackenzie\"}",
      "organization_id": null
    },
    {
      "name": "Rob Kauffman",
      "classification": "cosponsor",
      "entity_type": "person",
      "primary": false,
      "person_id": "~{\"chamber\": \"lower\", \"name\": \"Rob Kauffman\"}",
      "organization_id": null
    },
    {
      "name": "Aaron Bernstine",
      "classification": "cosponsor",
      "entity_type": "person",
      "primary": false,
      "person_id": "~{\"chamber\": \"lower\", \"name\": \"Aaron Bernstine\"}",
      "organization_id": null
    },
    {
      "name": "Keith Harris",
      "classification": "cosponsor",
      "entity_type": "person",
      "primary": false,
      "person_id": "~{\"chamber\": \"lower\", \"name\": \"Keith Harris\"}",
      "organization_id": null
    }
  ],
  "related_bills": [],
  "versions": [
    {
      "note": "Printer's No. PN0623",
      "links": [
        {
          "url": "https://www.palegis.us/legislation/bills/text/PDF/2025/0/HB0610/PN0623",
          "media_type": "application/pdf"
        },
        {
          "url": "https://www.palegis.us/legislation/bills/text/HTM/2025/0/HB0610/PN0623",
          "media_type": "text/html"
        },
        {
          "url": "https://www.palegis.us/legislation/bills/text/DOC/2025/0/HB0610/PN0623",
          "media_type": "application/msword"
        }
      ],
      "date": "",
      "classification": ""
    }
  ],
  "documents": [],
  "citations": [],
  "sources": [
    {
      "url": "https://www.palegis.us/legislation/bills/2025/hb610",
      "note": ""
    }
  ],
  "extras": {},
  "jurisdiction": {
    "id": "ocd-jurisdiction/country:us/state:pa/government",
    "name": "Pennsylvania",
    "classification": "state",
    "division_id": "ocd-division/country:us/state:pa"
  },
  "_processing": {
    "logs_latest_update": "2025-10-25T03:31:41Z",
    "text_extraction_latest_update": "2025-10-25T10:09:55.598848Z"
  }
}