{
  "legislative_session": "2025-2026",
  "identifier": "SB 520",
  "title": "An Act amending Titles 18 (Crimes and Offenses), 30 (Fish), 34 (Game), 42 (Judiciary and Judicial Procedure) and 61 (Prisons and Parole) of the Pennsylvania Consolidated Statutes, in wiretapping and electronic surveillance, further providing for definitions and repealing provisions relating to public access; in enforcement relating to fish, further providing for powers and duties of waterways conservation officers and deputies; in enforcement relating to game, further providing for powers and duties of enforcement officers; in recordings by law enforcement officers, further providing for definitions and for audio recording or video recording policies; in Pennsylvania Board of Probation and Parole, further providing for powers and duties of Department of Corrections; and making transfers between the State Gaming Fund and certain restricted accounts.",
  "from_organization": "~{\"classification\": \"upper\"}",
  "classification": [
    "bill"
  ],
  "subject": [],
  "abstracts": [],
  "other_titles": [],
  "other_identifiers": [],
  "actions": [
    {
      "description": "Referred to Judiciary",
      "date": "2025-03-26T04:00:00+00:00",
      "organization_id": "~{\"classification\": \"upper\"}",
      "classification": [
        "referral-committee"
      ],
      "related_entities": [],
      "_processing": {
        "log_file_created": "2025-10-25T03:31:42Z"
      }
    },
    {
      "description": "Reported as committed",
      "date": "2025-04-01T04:00:00+00:00",
      "organization_id": "~{\"classification\": \"upper\"}",
      "classification": [
        "committee-passage"
      ],
      "related_entities": [],
      "_processing": {
        "log_file_created": "2025-10-25T03:31:42Z"
      }
    },
    {
      "description": "First consideration",
      "date": "2025-04-01T04:00:00+00:00",
      "organization_id": "~{\"classification\": \"upper\"}",
      "classification": [
        "reading-1"
      ],
      "related_entities": [],
      "_processing": {
        "log_file_created": "2025-10-25T03:31:42Z"
      }
    },
    {
      "description": "Second consideration",
      "date": "2025-04-02T04:00:00+00:00",
      "organization_id": "~{\"classification\": \"upper\"}",
      "classification": [
        "reading-2"
      ],
      "related_entities": [],
      "_processing": {
        "log_file_created": "2025-10-25T03:31:42Z"
      }
    },
    {
      "description": "Re-referred to Appropriations",
      "date": "2025-04-02T04:00:00+00:00",
      "organization_id": "~{\"classification\": \"upper\"}",
      "classification": [
        "referral-committee"
      ],
      "related_entities": [],
      "_processing": {
        "log_file_created": "2025-10-25T03:31:42Z"
      }
    },
    {
      "description": "Re-reported as amended",
      "date": "2025-06-25T04:00:00+00:00",
      "organization_id": "~{\"classification\": \"upper\"}",
      "classification": [
        "amendment-passage",
        "committee-passage"
      ],
      "related_entities": [],
      "_processing": {
        "log_file_created": "2025-10-25T03:31:42Z"
      }
    },
    {
      "description": "Amended on third consideration",
      "date": "2025-06-25T04:00:00+00:00",
      "organization_id": "~{\"classification\": \"upper\"}",
      "classification": [
        "amendment-passage"
      ],
      "related_entities": [],
      "_processing": {
        "log_file_created": "2025-10-25T03:31:42Z"
      }
    },
    {
      "description": "Third consideration and final passage",
      "date": "2025-06-26T04:00:00+00:00",
      "organization_id": "~{\"classification\": \"upper\"}",
      "classification": [
        "passage",
        "reading-3"
      ],
      "related_entities": [],
      "_processing": {
        "log_file_created": "2025-10-25T03:31:42Z"
      }
    },
    {
      "description": "Referred to Judiciary",
      "date": "2025-06-30T04:00:00+00:00",
      "organization_id": "~{\"classification\": \"lower\"}",
      "classification": [
        "referral-committee"
      ],
      "related_entities": [],
      "_processing": {
        "log_file_created": "2025-10-25T03:31:42Z"
      }
    },
    {
      "description": "Reported as committed",
      "date": "2025-07-14T04:00:00+00:00",
      "organization_id": "~{\"classification\": \"lower\"}",
      "classification": [
        "committee-passage"
      ],
      "related_entities": [],
      "_processing": {
        "log_file_created": "2025-10-25T03:31:42Z"
      }
    },
    {
      "description": "First consideration",
      "date": "2025-07-14T04:00:00+00:00",
      "organization_id": "~{\"classification\": \"lower\"}",
      "classification": [
        "reading-1"
      ],
      "related_entities": [],
      "_processing": {
        "log_file_created": "2025-10-25T03:31:42Z"
      }
    },
    {
      "description": "Laid on the table",
      "date": "2025-07-14T04:00:00+00:00",
      "organization_id": "~{\"classification\": \"lower\"}",
      "classification": [],
      "related_entities": [],
      "_processing": {
        "log_file_created": "2025-10-25T03:31:42Z"
      }
    }
  ],
  "sponsorships": [
    {
      "name": "Lisa Baker",
      "classification": "primary",
      "entity_type": "person",
      "primary": true,
      "person_id": "~{\"chamber\": \"upper\", \"name\": \"Lisa Baker\"}",
      "organization_id": null
    },
    {
      "name": "Tracy Pennycuick",
      "classification": "cosponsor",
      "entity_type": "person",
      "primary": false,
      "person_id": "~{\"chamber\": \"upper\", \"name\": \"Tracy Pennycuick\"}",
      "organization_id": null
    },
    {
      "name": "Devlin Robinson",
      "classification": "cosponsor",
      "entity_type": "person",
      "primary": false,
      "person_id": "~{\"chamber\": \"upper\", \"name\": \"Devlin Robinson\"}",
      "organization_id": null
    },
    {
      "name": "Camera Bartolotta",
      "classification": "cosponsor",
      "entity_type": "person",
      "primary": false,
      "person_id": "~{\"chamber\": \"upper\", \"name\": \"Camera Bartolotta\"}",
      "organization_id": null
    },
    {
      "name": "Rosemary Brown",
      "classification": "cosponsor",
      "entity_type": "person",
      "primary": false,
      "person_id": "~{\"chamber\": \"upper\", \"name\": \"Rosemary Brown\"}",
      "organization_id": null
    },
    {
      "name": "Jay Costa",
      "classification": "cosponsor",
      "entity_type": "person",
      "primary": false,
      "person_id": "~{\"chamber\": \"upper\", \"name\": \"Jay Costa\"}",
      "organization_id": null
    },
    {
      "name": "John Kane",
      "classification": "cosponsor",
      "entity_type": "person",
      "primary": false,
      "person_id": "~{\"chamber\": \"upper\", \"name\": \"John Kane\"}",
      "organization_id": null
    },
    {
      "name": "Judy Ward",
      "classification": "cosponsor",
      "entity_type": "person",
      "primary": false,
      "person_id": "~{\"chamber\": \"upper\", \"name\": \"Judy Ward\"}",
      "organization_id": null
    },
    {
      "name": "Nick Miller",
      "classification": "cosponsor",
      "entity_type": "person",
      "primary": false,
      "person_id": "~{\"chamber\": \"upper\", \"name\": \"Nick Miller\"}",
      "organization_id": null
    },
    {
      "name": "Patrick Stefano",
      "classification": "cosponsor",
      "entity_type": "person",
      "primary": false,
      "person_id": "~{\"chamber\": \"upper\", \"name\": \"Patrick Stefano\"}",
      "organization_id": null
    },
    {
      "name": "Judith Schwank",
      "classification": "cosponsor",
      "entity_type": "person",
      "primary": false,
      "person_id": "~{\"chamber\": \"upper\", \"name\": \"Judith Schwank\"}",
      "organization_id": null
    },
    {
      "name": "Cris Dush",
      "classification": "cosponsor",
      "entity_type": "person",
      "primary": false,
      "person_id": "~{\"chamber\": \"upper\", \"name\": \"Cris Dush\"}",
      "organization_id": null
    }
  ],
  "related_bills": [],
  "versions": [
    {
      "note": "Printer's No. PN1010",
      "links": [
        {
          "url": "https://www.palegis.us/legislation/bills/text/PDF/2025/0/SB0520/PN1010",
          "media_type": "application/pdf"
        },
        {
          "url": "https://www.palegis.us/legislation/bills/text/HTM/2025/0/SB0520/PN1010",
          "media_type": "text/html"
        },
        {
          "url": "https://www.palegis.us/legislation/bills/text/DOC/2025/0/SB0520/PN1010",
          "media_type": "application/msword"
        }
      ],
      "date": "",
      "classification": ""
    },
    {
      "note": "Printer's No. PN1008",
      "links": [
        {
          "url": "https://www.palegis.us/legislation/bills/text/PDF/2025/0/SB0520/PN1008",
          "media_type": "application/pdf"
        },
        {
          "url": "https://www.palegis.us/legislation/bills/text/HTM/2025/0/SB0520/PN1008",
          "media_type": "text/html"
        },
        {
          "url": "https://www.palegis.us/legislation/bills/text/DOC/2025/0/SB0520/PN1008",
          "media_type": "application/msword"
        }
      ],
      "date": "",
      "classification": ""
    },
    {
      "note": "Printer's No. PN0489",
      "links": [
        {
          "url": "https://www.palegis.us/legislation/bills/text/PDF/2025/0/SB0520/PN0489",
          "media_type": "application/pdf"
        },
        {
          "url": "https://www.palegis.us/legislation/bills/text/HTM/2025/0/SB0520/PN0489",
          "media_type": "text/html"
        },
        {
          "url": "https://www.palegis.us/legislation/bills/text/DOC/2025/0/SB0520/PN0489",
          "media_type": "application/msword"
        }
      ],
      "date": "",
      "classification": ""
    }
  ],
  "documents": [
    {
      "note": "Senate Fiscal Note",
      "links": [
        {
          "url": "https://www.legis.state.pa.us/WU01/LI/BI/SFN/2025/0/SB0520P1008.pdf",
          "media_type": "application/pdf"
        }
      ],
      "date": "",
      "classification": ""
    }
  ],
  "citations": [],
  "sources": [
    {
      "url": "https://www.palegis.us/legislation/bills/2025/sb520",
      "note": ""
    },
    {
      "url": "https://www.palegis.us/house/committees/roll-call-votes/vote-list/vote-summary?committeecode=60&rollcallid=1072&sessYr=2025&sessInd=0",
      "note": ""
    },
    {
      "url": "https://www.palegis.us/senate/roll-calls/summary?sessYr=2025&sessInd=0&rcNum=159",
      "note": ""
    },
    {
      "url": "https://www.palegis.us/senate/committees/roll-call-votes/vote-list/vote-summary?committeecode=3&rollcallid=368&sessYr=2025&sessInd=0",
      "note": ""
    },
    {
      "url": "https://www.palegis.us/senate/committees/roll-call-votes/vote-list/vote-summary?committeecode=3&rollcallid=369&sessYr=2025&sessInd=0",
      "note": ""
    },
    {
      "url": "https://www.palegis.us/senate/committees/roll-call-votes/vote-list/vote-summary?committeecode=39&rollcallid=106&sessYr=2025&sessInd=0",
      "note": ""
    }
  ],
  "extras": {},
  "jurisdiction": {
    "id": "ocd-jurisdiction/country:us/state:pa/government",
    "name": "Pennsylvania",
    "classification": "state",
    "division_id": "ocd-division/country:us/state:pa"
  },
  "_processing": {
    "logs_latest_update": "2025-10-25T03:31:42Z"
  }
}