{
  "legislative_session": "2025-2026",
  "identifier": "HB 1041",
  "title": "An Act amending the act of April 12, 1951 (P.L.90, No.21), known as the Liquor Code, in licenses and regulations and liquor, alcohol and malt and brewed beverages, further providing for breweries; and, in distilleries, wineries, bonded warehouses, bailees for hire and transporters for hire, further providing for limited distilleries and distilleries.",
  "from_organization": "~{\"classification\": \"lower\"}",
  "classification": [
    "bill"
  ],
  "subject": [],
  "abstracts": [],
  "other_titles": [],
  "other_identifiers": [],
  "actions": [
    {
      "description": "Referred to Liquor Control",
      "date": "2025-03-25T04:00:00+00:00",
      "organization_id": "~{\"classification\": \"lower\"}",
      "classification": [
        "referral-committee"
      ],
      "related_entities": [],
      "_processing": {
        "log_file_created": "2025-10-25T03:31:45Z"
      }
    }
  ],
  "sponsorships": [
    {
      "name": "Jonathan Fritz",
      "classification": "primary",
      "entity_type": "person",
      "primary": true,
      "person_id": "~{\"chamber\": \"lower\", \"name\": \"Jonathan Fritz\"}",
      "organization_id": null
    },
    {
      "name": "Steven Malagari",
      "classification": "cosponsor",
      "entity_type": "person",
      "primary": false,
      "person_id": "~{\"chamber\": \"lower\", \"name\": \"Steven Malagari\"}",
      "organization_id": null
    },
    {
      "name": "Mindy Fee",
      "classification": "cosponsor",
      "entity_type": "person",
      "primary": false,
      "person_id": "~{\"chamber\": \"lower\", \"name\": \"Mindy Fee\"}",
      "organization_id": null
    },
    {
      "name": "Danielle Friel Otten",
      "classification": "cosponsor",
      "entity_type": "person",
      "primary": false,
      "person_id": "~{\"chamber\": \"lower\", \"name\": \"Danielle Friel Otten\"}",
      "organization_id": null
    },
    {
      "name": "Tina Pickett",
      "classification": "cosponsor",
      "entity_type": "person",
      "primary": false,
      "person_id": "~{\"chamber\": \"lower\", \"name\": \"Tina Pickett\"}",
      "organization_id": null
    },
    {
      "name": "Nancy Guenst",
      "classification": "cosponsor",
      "entity_type": "person",
      "primary": false,
      "person_id": "~{\"chamber\": \"lower\", \"name\": \"Nancy Guenst\"}",
      "organization_id": null
    },
    {
      "name": "Brian Smith",
      "classification": "cosponsor",
      "entity_type": "person",
      "primary": false,
      "person_id": "~{\"chamber\": \"lower\", \"name\": \"Brian Smith\"}",
      "organization_id": null
    },
    {
      "name": "Jeff Olsommer",
      "classification": "cosponsor",
      "entity_type": "person",
      "primary": false,
      "person_id": "~{\"chamber\": \"lower\", \"name\": \"Jeff Olsommer\"}",
      "organization_id": null
    },
    {
      "name": "Jose Giral",
      "classification": "cosponsor",
      "entity_type": "person",
      "primary": false,
      "person_id": "~{\"chamber\": \"lower\", \"name\": \"Jose Giral\"}",
      "organization_id": null
    },
    {
      "name": "R. Lee James",
      "classification": "cosponsor",
      "entity_type": "person",
      "primary": false,
      "person_id": "~{\"chamber\": \"lower\", \"name\": \"R. Lee James\"}",
      "organization_id": null
    },
    {
      "name": "Michael Stender",
      "classification": "cosponsor",
      "entity_type": "person",
      "primary": false,
      "person_id": "~{\"chamber\": \"lower\", \"name\": \"Michael Stender\"}",
      "organization_id": null
    },
    {
      "name": "Johanny Cepeda-Freytiz",
      "classification": "cosponsor",
      "entity_type": "person",
      "primary": false,
      "person_id": "~{\"chamber\": \"lower\", \"name\": \"Johanny Cepeda-Freytiz\"}",
      "organization_id": null
    },
    {
      "name": "Mandy Steele",
      "classification": "cosponsor",
      "entity_type": "person",
      "primary": false,
      "person_id": "~{\"chamber\": \"lower\", \"name\": \"Mandy Steele\"}",
      "organization_id": null
    },
    {
      "name": "Joe Ciresi",
      "classification": "cosponsor",
      "entity_type": "person",
      "primary": false,
      "person_id": "~{\"chamber\": \"lower\", \"name\": \"Joe Ciresi\"}",
      "organization_id": null
    }
  ],
  "related_bills": [],
  "versions": [
    {
      "note": "Printer's No. PN1130",
      "links": [
        {
          "url": "https://www.palegis.us/legislation/bills/text/PDF/2025/0/HB1041/PN1130",
          "media_type": "application/pdf"
        },
        {
          "url": "https://www.palegis.us/legislation/bills/text/HTM/2025/0/HB1041/PN1130",
          "media_type": "text/html"
        },
        {
          "url": "https://www.palegis.us/legislation/bills/text/DOC/2025/0/HB1041/PN1130",
          "media_type": "application/msword"
        }
      ],
      "date": "",
      "classification": ""
    }
  ],
  "documents": [],
  "citations": [],
  "sources": [
    {
      "url": "https://www.palegis.us/legislation/bills/2025/hb1041",
      "note": ""
    }
  ],
  "extras": {},
  "jurisdiction": {
    "id": "ocd-jurisdiction/country:us/state:pa/government",
    "name": "Pennsylvania",
    "classification": "state",
    "division_id": "ocd-division/country:us/state:pa"
  },
  "_processing": {
    "logs_latest_update": "2025-10-25T03:31:45Z",
    "text_extraction_latest_update": "2025-10-25T09:25:32.305840Z"
  }
}