{
  "legislative_session": "2025-2026",
  "identifier": "HB 1349",
  "title": "An Act amending Title 74 (Transportation) of the Pennsylvania Consolidated Statutes, in administrative practice and procedure, providing for project labor agreement.",
  "from_organization": "~{\"classification\": \"lower\"}",
  "classification": [
    "bill"
  ],
  "subject": [],
  "abstracts": [],
  "other_titles": [],
  "other_identifiers": [],
  "actions": [
    {
      "description": "Referred to Labor & Industry",
      "date": "2025-04-30T04:00:00+00:00",
      "organization_id": "~{\"classification\": \"lower\"}",
      "classification": [
        "referral-committee"
      ],
      "related_entities": [],
      "_processing": {
        "log_file_created": "2025-10-25T03:31:43Z"
      }
    }
  ],
  "sponsorships": [
    {
      "name": "Carol Kazeem",
      "classification": "primary",
      "entity_type": "person",
      "primary": true,
      "person_id": "~{\"chamber\": \"lower\", \"name\": \"Carol Kazeem\"}",
      "organization_id": null
    },
    {
      "name": "Jose Giral",
      "classification": "cosponsor",
      "entity_type": "person",
      "primary": false,
      "person_id": "~{\"chamber\": \"lower\", \"name\": \"Jose Giral\"}",
      "organization_id": null
    },
    {
      "name": "Jeanne Mcneill",
      "classification": "cosponsor",
      "entity_type": "person",
      "primary": false,
      "person_id": "~{\"chamber\": \"lower\", \"name\": \"Jeanne Mcneill\"}",
      "organization_id": null
    },
    {
      "name": "Carol Hill-Evans",
      "classification": "cosponsor",
      "entity_type": "person",
      "primary": false,
      "person_id": "~{\"chamber\": \"lower\", \"name\": \"Carol Hill-Evans\"}",
      "organization_id": null
    },
    {
      "name": "Maureen Madden",
      "classification": "cosponsor",
      "entity_type": "person",
      "primary": false,
      "person_id": "~{\"chamber\": \"lower\", \"name\": \"Maureen Madden\"}",
      "organization_id": null
    },
    {
      "name": "Steven Malagari",
      "classification": "cosponsor",
      "entity_type": "person",
      "primary": false,
      "person_id": "~{\"chamber\": \"lower\", \"name\": \"Steven Malagari\"}",
      "organization_id": null
    },
    {
      "name": "Jennifer O'Mara",
      "classification": "cosponsor",
      "entity_type": "person",
      "primary": false,
      "person_id": "~{\"chamber\": \"lower\", \"name\": \"Jennifer O'Mara\"}",
      "organization_id": null
    },
    {
      "name": "Ed Neilson",
      "classification": "cosponsor",
      "entity_type": "person",
      "primary": false,
      "person_id": "~{\"chamber\": \"lower\", \"name\": \"Ed Neilson\"}",
      "organization_id": null
    },
    {
      "name": "Benjamin Sanchez",
      "classification": "cosponsor",
      "entity_type": "person",
      "primary": false,
      "person_id": "~{\"chamber\": \"lower\", \"name\": \"Benjamin Sanchez\"}",
      "organization_id": null
    },
    {
      "name": "Dan Williams",
      "classification": "cosponsor",
      "entity_type": "person",
      "primary": false,
      "person_id": "~{\"chamber\": \"lower\", \"name\": \"Dan Williams\"}",
      "organization_id": null
    },
    {
      "name": "Anthony Bellmon",
      "classification": "cosponsor",
      "entity_type": "person",
      "primary": false,
      "person_id": "~{\"chamber\": \"lower\", \"name\": \"Anthony Bellmon\"}",
      "organization_id": null
    },
    {
      "name": "Lisa Borowski",
      "classification": "cosponsor",
      "entity_type": "person",
      "primary": false,
      "person_id": "~{\"chamber\": \"lower\", \"name\": \"Lisa Borowski\"}",
      "organization_id": null
    },
    {
      "name": "Keith Harris",
      "classification": "cosponsor",
      "entity_type": "person",
      "primary": false,
      "person_id": "~{\"chamber\": \"lower\", \"name\": \"Keith Harris\"}",
      "organization_id": null
    }
  ],
  "related_bills": [],
  "versions": [
    {
      "note": "Printer's No. PN1537",
      "links": [
        {
          "url": "https://www.palegis.us/legislation/bills/text/PDF/2025/0/HB1349/PN1537",
          "media_type": "application/pdf"
        },
        {
          "url": "https://www.palegis.us/legislation/bills/text/HTM/2025/0/HB1349/PN1537",
          "media_type": "text/html"
        },
        {
          "url": "https://www.palegis.us/legislation/bills/text/DOC/2025/0/HB1349/PN1537",
          "media_type": "application/msword"
        }
      ],
      "date": "",
      "classification": ""
    }
  ],
  "documents": [],
  "citations": [],
  "sources": [
    {
      "url": "https://www.palegis.us/legislation/bills/2025/hb1349",
      "note": ""
    }
  ],
  "extras": {},
  "jurisdiction": {
    "id": "ocd-jurisdiction/country:us/state:pa/government",
    "name": "Pennsylvania",
    "classification": "state",
    "division_id": "ocd-division/country:us/state:pa"
  },
  "_processing": {
    "logs_latest_update": "2025-10-25T03:31:43Z",
    "text_extraction_latest_update": "2025-10-25T08:43:38.350004Z"
  }
}