{
  "legislative_session": "2025-2026",
  "identifier": "SB 928",
  "title": "An Act amending the act of January 25, 1966 (1965 P.L.1542, No.538), entitled \"An act creating a Commonwealth of Pennsylvania Council on the Arts, for the encouragement and development of the various arts, and making an appropriation therefor,\" establishing the Pennsylvania Film Producer Grant Program and the Pennsylvania Film Producer Grant Program Account; and making a repeal.",
  "from_organization": "~{\"classification\": \"upper\"}",
  "classification": [
    "bill"
  ],
  "subject": [],
  "abstracts": [],
  "other_titles": [],
  "other_identifiers": [],
  "actions": [
    {
      "description": "Referred to State Government",
      "date": "2025-07-23T04:00:00+00:00",
      "organization_id": "~{\"classification\": \"upper\"}",
      "classification": [
        "referral-committee"
      ],
      "related_entities": [],
      "_processing": {
        "log_file_created": "2025-10-25T03:31:42Z"
      }
    }
  ],
  "sponsorships": [
    {
      "name": "Camera Bartolotta",
      "classification": "primary",
      "entity_type": "person",
      "primary": true,
      "person_id": "~{\"chamber\": \"upper\", \"name\": \"Camera Bartolotta\"}",
      "organization_id": null
    },
    {
      "name": "Wayne Fontana",
      "classification": "cosponsor",
      "entity_type": "person",
      "primary": false,
      "person_id": "~{\"chamber\": \"upper\", \"name\": \"Wayne Fontana\"}",
      "organization_id": null
    },
    {
      "name": "Jay Costa",
      "classification": "cosponsor",
      "entity_type": "person",
      "primary": false,
      "person_id": "~{\"chamber\": \"upper\", \"name\": \"Jay Costa\"}",
      "organization_id": null
    },
    {
      "name": "Frank Farry",
      "classification": "cosponsor",
      "entity_type": "person",
      "primary": false,
      "person_id": "~{\"chamber\": \"upper\", \"name\": \"Frank Farry\"}",
      "organization_id": null
    },
    {
      "name": "Devlin Robinson",
      "classification": "cosponsor",
      "entity_type": "person",
      "primary": false,
      "person_id": "~{\"chamber\": \"upper\", \"name\": \"Devlin Robinson\"}",
      "organization_id": null
    }
  ],
  "related_bills": [],
  "versions": [
    {
      "note": "Printer's No. PN1063",
      "links": [
        {
          "url": "https://www.palegis.us/legislation/bills/text/PDF/2025/0/SB0928/PN1063",
          "media_type": "application/pdf"
        },
        {
          "url": "https://www.palegis.us/legislation/bills/text/HTM/2025/0/SB0928/PN1063",
          "media_type": "text/html"
        },
        {
          "url": "https://www.palegis.us/legislation/bills/text/DOC/2025/0/SB0928/PN1063",
          "media_type": "application/msword"
        }
      ],
      "date": "",
      "classification": ""
    }
  ],
  "documents": [],
  "citations": [],
  "sources": [
    {
      "url": "https://www.palegis.us/legislation/bills/2025/sb928",
      "note": ""
    }
  ],
  "extras": {},
  "jurisdiction": {
    "id": "ocd-jurisdiction/country:us/state:pa/government",
    "name": "Pennsylvania",
    "classification": "state",
    "division_id": "ocd-division/country:us/state:pa"
  },
  "_processing": {
    "logs_latest_update": "2025-10-25T03:31:42Z"
  }
}