{
  "legislative_session": "2025-2026",
  "identifier": "HB 1109",
  "title": "An Act amending Title 20 (Decedents, Estates and Fiduciaries) of the Pennsylvania Consolidated Statutes, providing for compassionate aid in dying; and imposing penalties.",
  "from_organization": "~{\"classification\": \"lower\"}",
  "classification": [
    "bill"
  ],
  "subject": [],
  "abstracts": [],
  "other_titles": [],
  "other_identifiers": [],
  "actions": [
    {
      "description": "Referred to Judiciary",
      "date": "2025-04-03T04:00:00+00:00",
      "organization_id": "~{\"classification\": \"lower\"}",
      "classification": [
        "referral-committee"
      ],
      "related_entities": [],
      "_processing": {
        "log_file_created": "2025-10-25T03:31:41Z"
      }
    }
  ],
  "sponsorships": [
    {
      "name": "Carol Hill-Evans",
      "classification": "primary",
      "entity_type": "person",
      "primary": true,
      "person_id": "~{\"chamber\": \"lower\", \"name\": \"Carol Hill-Evans\"}",
      "organization_id": null
    },
    {
      "name": "Tarik Khan",
      "classification": "cosponsor",
      "entity_type": "person",
      "primary": false,
      "person_id": "~{\"chamber\": \"lower\", \"name\": \"Tarik Khan\"}",
      "organization_id": null
    },
    {
      "name": "Melissa Shusterman",
      "classification": "cosponsor",
      "entity_type": "person",
      "primary": false,
      "person_id": "~{\"chamber\": \"lower\", \"name\": \"Melissa Shusterman\"}",
      "organization_id": null
    },
    {
      "name": "Christopher Rabb",
      "classification": "cosponsor",
      "entity_type": "person",
      "primary": false,
      "person_id": "~{\"chamber\": \"lower\", \"name\": \"Christopher Rabb\"}",
      "organization_id": null
    },
    {
      "name": "Jose Giral",
      "classification": "cosponsor",
      "entity_type": "person",
      "primary": false,
      "person_id": "~{\"chamber\": \"lower\", \"name\": \"Jose Giral\"}",
      "organization_id": null
    },
    {
      "name": "Benjamin Sanchez",
      "classification": "cosponsor",
      "entity_type": "person",
      "primary": false,
      "person_id": "~{\"chamber\": \"lower\", \"name\": \"Benjamin Sanchez\"}",
      "organization_id": null
    },
    {
      "name": "Maureen Madden",
      "classification": "cosponsor",
      "entity_type": "person",
      "primary": false,
      "person_id": "~{\"chamber\": \"lower\", \"name\": \"Maureen Madden\"}",
      "organization_id": null
    },
    {
      "name": "La'Tasha Mayes",
      "classification": "cosponsor",
      "entity_type": "person",
      "primary": false,
      "person_id": "~{\"chamber\": \"lower\", \"name\": \"La'Tasha Mayes\"}",
      "organization_id": null
    },
    {
      "name": "Rick Krajewski",
      "classification": "cosponsor",
      "entity_type": "person",
      "primary": false,
      "person_id": "~{\"chamber\": \"lower\", \"name\": \"Rick Krajewski\"}",
      "organization_id": null
    },
    {
      "name": "Tarah Probst",
      "classification": "cosponsor",
      "entity_type": "person",
      "primary": false,
      "person_id": "~{\"chamber\": \"lower\", \"name\": \"Tarah Probst\"}",
      "organization_id": null
    },
    {
      "name": "Melissa Cerrato",
      "classification": "cosponsor",
      "entity_type": "person",
      "primary": false,
      "person_id": "~{\"chamber\": \"lower\", \"name\": \"Melissa Cerrato\"}",
      "organization_id": null
    },
    {
      "name": "Dan Williams",
      "classification": "cosponsor",
      "entity_type": "person",
      "primary": false,
      "person_id": "~{\"chamber\": \"lower\", \"name\": \"Dan Williams\"}",
      "organization_id": null
    },
    {
      "name": "G. Roni Green",
      "classification": "cosponsor",
      "entity_type": "person",
      "primary": false,
      "person_id": "~{\"chamber\": \"lower\", \"name\": \"G. Roni Green\"}",
      "organization_id": null
    },
    {
      "name": "Joe Ciresi",
      "classification": "cosponsor",
      "entity_type": "person",
      "primary": false,
      "person_id": "~{\"chamber\": \"lower\", \"name\": \"Joe Ciresi\"}",
      "organization_id": null
    },
    {
      "name": "John Inglis Iii",
      "classification": "cosponsor",
      "entity_type": "person",
      "primary": false,
      "person_id": "~{\"chamber\": \"lower\", \"name\": \"John Inglis Iii\"}",
      "organization_id": null
    }
  ],
  "related_bills": [],
  "versions": [
    {
      "note": "Printer's No. PN1233",
      "links": [
        {
          "url": "https://www.palegis.us/legislation/bills/text/PDF/2025/0/HB1109/PN1233",
          "media_type": "application/pdf"
        },
        {
          "url": "https://www.palegis.us/legislation/bills/text/HTM/2025/0/HB1109/PN1233",
          "media_type": "text/html"
        },
        {
          "url": "https://www.palegis.us/legislation/bills/text/DOC/2025/0/HB1109/PN1233",
          "media_type": "application/msword"
        }
      ],
      "date": "",
      "classification": ""
    }
  ],
  "documents": [],
  "citations": [],
  "sources": [
    {
      "url": "https://www.palegis.us/legislation/bills/2025/hb1109",
      "note": ""
    }
  ],
  "extras": {},
  "jurisdiction": {
    "id": "ocd-jurisdiction/country:us/state:pa/government",
    "name": "Pennsylvania",
    "classification": "state",
    "division_id": "ocd-division/country:us/state:pa"
  },
  "_processing": {
    "logs_latest_update": "2025-10-25T03:31:41Z",
    "text_extraction_latest_update": "2025-10-25T09:36:48.461804Z"
  }
}